aihc_cli_py/__init__.py
aihc_cli_py/aihc_argumentparser.py
aihc_cli_py/configure.py
aihc_cli_py/create_job_request.py
aihc_cli_py/job.py
aihc_cli_py/resourcepool.py
aihc_cli_py/resourcepool_queue.py
aihc_cli_py/runner.py
aihc_cli_py/utils.py
aihc_cli_py/doc/help_message.txt
aihc_cli_py/doc/job_help.message.txt
aihc_cli_py/doc/pool_help_message.txt
aihc_cli_py/doc/queue_help_message.txt
aihc-1.1.1.dist-info/LICENSE
aihc-1.1.1.dist-info/METADATA
aihc-1.1.1.dist-info/WHEEL
aihc-1.1.1.dist-info/entry_points.txt
aihc-1.1.1.dist-info/top_level.txt
aihc-1.1.1.dist-info/RECORD
