Metadata-Version: 2.1
Name: aihc
Version: 1.1.1
Summary: AIHC Command-Line Tool
Home-page: https://github.com/Baidu-AIHC/aihc_cli
Author: Baiduclear Corporation
Author-email: wangzhuyun@baidu.com
License: MIT
Classifier: Intended Audience :: Developers
Classifier: Operating System :: OS Independent
Classifier: Natural Language :: Chinese (Simplified)
Classifier: Programming Language :: Python
Classifier: Programming Language :: Python :: 2
Classifier: Programming Language :: Python :: 2.7
Classifier: Programming Language :: Python :: 3
Classifier: Programming Language :: Python :: 3.5
Classifier: Programming Language :: Python :: 3.6
Classifier: Programming Language :: Python :: 3.7
Classifier: Programming Language :: Python :: 3.8
Classifier: Topic :: Software Development :: Libraries
License-File: LICENSE
Requires-Dist: datetime
Requires-Dist: pandas
Requires-Dist: requests
